ksox/__init__.py
ksox/sox.py
ksox/soxi.py
ksox/models/__init__.py
ksox/models/concat_song_element.py
ksox/models/sox_stats.py
ksox-0.0.8.dist-info/METADATA
ksox-0.0.8.dist-info/WHEEL
ksox-0.0.8.dist-info/top_level.txt
ksox-0.0.8.dist-info/RECORD
