Metadata-Version: 2.1
Name: ksox
Version: 0.0.8
Summary: ksox utils
Home-page: https://github.com/kkristof200/py_ksox
Author: Kristof
License: UNKNOWN
Platform: UNKNOWN
Classifier: Programming Language :: Python :: 3
Classifier: License :: OSI Approved :: MIT License
Classifier: Operating System :: OS Independent
Requires-Python: >=3.5
Requires-Dist: kcu
Requires-Dist: jsoncodable
